snippy/__init__.py
snippy/cause.py
snippy/constants.py
snippy/logger.py
snippy/meta.py
snippy/plugins.py
snippy/snip.py
snippy/config/__init__.py
snippy/config/config.py
snippy/config/source/__init__.py
snippy/config/source/api.py
snippy/config/source/base.py
snippy/config/source/cli.py
snippy/config/source/editor.py
snippy/content/__init__.py
snippy/content/all_content.py
snippy/content/base.py
snippy/content/collection.py
snippy/content/content.py
snippy/content/fields.py
snippy/content/migrate.py
snippy/content/parser.py
snippy/content/resource.py
snippy/content/parsers/__init__.py
snippy/content/parsers/base.py
snippy/content/parsers/dict.py
snippy/content/parsers/mkdn.py
snippy/content/parsers/text.py
snippy/data/completion/snippy.bash-completion
snippy/data/defaults/references.yaml
snippy/data/defaults/snippets.yaml
snippy/data/defaults/solutions.yaml
snippy/data/server/openapi/schema/_definitions.json
snippy/data/server/openapi/schema/all.json
snippy/data/server/openapi/schema/attributebrief.json
snippy/data/server/openapi/schema/attributecategory.json
snippy/data/server/openapi/schema/attributecreated.json
snippy/data/server/openapi/schema/attributedata.json
snippy/data/server/openapi/schema/attributedescription.json
snippy/data/server/openapi/schema/attributedigest.json
snippy/data/server/openapi/schema/attributefilename.json
snippy/data/server/openapi/schema/attributegroups.json
snippy/data/server/openapi/schema/attributegroupsdictionary.json
snippy/data/server/openapi/schema/attributelanguages.json
snippy/data/server/openapi/schema/attributelinks.json
snippy/data/server/openapi/schema/attributename.json
snippy/data/server/openapi/schema/attributesource.json
snippy/data/server/openapi/schema/attributetags.json
snippy/data/server/openapi/schema/attributetagsdictionary.json
snippy/data/server/openapi/schema/attributeupdated.json
snippy/data/server/openapi/schema/attributeuuid.json
snippy/data/server/openapi/schema/attributeversions.json
snippy-0.11.0.dist-info/LICENSE
snippy-0.11.0.dist-info/METADATA
snippy-0.11.0.dist-info/WHEEL
snippy-0.11.0.dist-info/entry_points.txt
snippy-0.11.0.dist-info/top_level.txt
snippy-0.11.0.dist-info/RECORD
