Metadata-Version: 2.1
Name: snippy
Version: 0.11.0
Summary: Snippy is a software development and maintenance notes manager.
Home-page: https://github.com/heilaaks/snippy
Author: Heikki J. Laaksonen
Author-email: laaksonen.heikki.j@gmail.com
License: GNU Affero General Public License v3.0 or later
Keywords: notes markdown yaml text command-line cli server backend docker software-engineering
Platform: Linux
Platform: MacOS
Platform: Microsoft
Classifier: Development Status :: 4 - Beta
Classifier: Environment :: Console
Classifier: Environment :: Web Environment
Classifier: Intended Audience :: Developers
Classifier: Intended Audience :: Information Technology
Classifier: License :: OSI Approved :: GNU Affero General Public License v3 or later (AGPLv3+)
Classifier: Natural Language :: English
Classifier: Operating System :: MacOS
Classifier: Operating System :: Microsoft
Classifier: Operating System :: POSIX :: Linux
Classifier: Programming Language :: Python :: 2
Classifier: Programming Language :: Python :: 2.7
Classifier: Programming Language :: Python :: 3
Classifier: Programming Language :: Python :: 3.4
Classifier: Programming Language :: Python :: 3.5
Classifier: Programming Language :: Python :: 3.6
Classifier: Programming Language :: Python :: 3.7
Classifier: Programming Language :: Python :: 3.8
Classifier: Programming Language :: Python :: Implementation :: CPython
Classifier: Programming Language :: Python :: Implementation :: PyPy
Classifier: Topic :: Software Development :: Documentation
Classifier: Topic :: Utilities
Requires-Python: >=2.7, !=3.0.*, !=3.1.*, !=3.2.*, !=3.3.*
Requires-Dist: importlib-metadata ; python_version != "3.4"
Requires-Dist: pyyaml ; python_version != "3.4"
Requires-Dist: importlib-metadata (==0.23) ; python_version == "3.4"
Requires-Dist: pyyaml (<=5.2) ; python_version == "3.4"
Requires-Dist: colorama ; sys_platform == "win32"
Provides-Extra: devel
Requires-Dist: sphinxcontrib-openapi (==0.6.0) ; extra == 'devel'
Requires-Dist: sphinx-rtd-theme (==0.4.3) ; extra == 'devel'
Requires-Dist: sphinx-autobuild (==0.7.1) ; extra == 'devel'
Requires-Dist: falcon (==2.0.0) ; extra == 'devel'
Requires-Dist: jsonschema (==3.2.0) ; extra == 'devel'
Requires-Dist: bandit (==1.6.2) ; extra == 'devel'
Requires-Dist: flake8 (==3.7.9) ; extra == 'devel'
Requires-Dist: logging-tree (==1.8.1) ; extra == 'devel'
Requires-Dist: pluggy (==0.13.1) ; extra == 'devel'
Requires-Dist: pprintpp (==0.4.0) ; extra == 'devel'
Requires-Dist: pyflakes (==2.1.1) ; extra == 'devel'
Requires-Dist: pytest-cov (==2.8.1) ; extra == 'devel'
Requires-Dist: pytest-mock (==2.0.0) ; extra == 'devel'
Requires-Dist: pytest-xdist (==1.31.0) ; extra == 'devel'
Requires-Dist: requests ; extra == 'devel'
Requires-Dist: psycopg2 (==2.8.4) ; (platform_python_implementation == "CPython") and extra == 'devel'
Requires-Dist: psycopg2cffi (==2.8.1) ; (platform_python_implementation == "PyPy") and extra == 'devel'
Requires-Dist: colorama ; (python_version != "3.4") and extra == 'devel'
Requires-Dist: gunicorn (==19.10.0) ; (python_version <= "3.3") and extra == 'devel'
Requires-Dist: sphinx (==1.8.5) ; (python_version <= "3.4") and extra == 'devel'
Requires-Dist: pytest (==4.6.9) ; (python_version <= "3.4") and extra == 'devel'
Requires-Dist: mock (==3.0.5) ; (python_version <= "3.5") and extra == 'devel'
Requires-Dist: openapi2jsonschema (==0.9.0) ; (python_version <= "3.6") and extra == 'devel'
Requires-Dist: pylint (==1.9.5) ; (python_version == "2.7.*") and extra == 'devel'
Requires-Dist: docker (==4.2.0) ; (python_version == "2.7.*" or python_version >= "3.5") and extra == 'devel'
Requires-Dist: tox (==3.14.5) ; (python_version == "2.7.*" or python_version >= "3.5") and extra == 'devel'
Requires-Dist: colorama (==0.4.1) ; (python_version == "3.4") and extra == 'devel'
Requires-Dist: docker (==3.7.3) ; (python_version == "3.4.*") and extra == 'devel'
Requires-Dist: pylint (==2.3.1) ; (python_version == "3.4.*") and extra == 'devel'
Requires-Dist: tox (==3.14.0) ; (python_version == "3.4.*") and extra == 'devel'
Requires-Dist: gunicorn (==20.0.4) ; (python_version >= "3.4") and extra == 'devel'
Requires-Dist: sphinx (==2.4.4) ; (python_version >= "3.5") and extra == 'devel'
Requires-Dist: pylint (==2.4.4) ; (python_version >= "3.5") and extra == 'devel'
Requires-Dist: pytest (==5.3.5) ; (python_version >= "3.5") and extra == 'devel'
Requires-Dist: mock (==4.0.1) ; (python_version >= "3.6") and extra == 'devel'
Requires-Dist: openapi2jsonschema (==0.9.1) ; (python_version >= "3.7") and extra == 'devel'
Provides-Extra: docs
Requires-Dist: sphinxcontrib-openapi (==0.6.0) ; extra == 'docs'
Requires-Dist: sphinx-rtd-theme (==0.4.3) ; extra == 'docs'
Requires-Dist: sphinx-autobuild (==0.7.1) ; extra == 'docs'
Requires-Dist: sphinx (==1.8.5) ; (python_version <= "3.4") and extra == 'docs'
Requires-Dist: sphinx (==2.4.4) ; (python_version >= "3.5") and extra == 'docs'
Provides-Extra: server
Requires-Dist: falcon (==2.0.0) ; extra == 'server'
Requires-Dist: jsonschema (==3.2.0) ; extra == 'server'
Requires-Dist: psycopg2 (==2.8.4) ; (platform_python_implementation == "CPython") and extra == 'server'
Requires-Dist: psycopg2cffi (==2.8.1) ; (platform_python_implementation == "PyPy") and extra == 'server'
Requires-Dist: gunicorn (==19.10.0) ; (python_version <= "3.3") and extra == 'server'
Requires-Dist: gunicorn (==20.0.4) ; (python_version >= "3.4") and extra == 'server'
Provides-Extra: test
Requires-Dist: falcon (==2.0.0) ; extra == 'test'
Requires-Dist: jsonschema (==3.2.0) ; extra == 'test'
Requires-Dist: bandit (==1.6.2) ; extra == 'test'
Requires-Dist: flake8 (==3.7.9) ; extra == 'test'
Requires-Dist: logging-tree (==1.8.1) ; extra == 'test'
Requires-Dist: pluggy (==0.13.1) ; extra == 'test'
Requires-Dist: pprintpp (==0.4.0) ; extra == 'test'
Requires-Dist: pyflakes (==2.1.1) ; extra == 'test'
Requires-Dist: pytest-cov (==2.8.1) ; extra == 'test'
Requires-Dist: pytest-mock (==2.0.0) ; extra == 'test'
Requires-Dist: pytest-xdist (==1.31.0) ; extra == 'test'
Requires-Dist: requests ; extra == 'test'
Requires-Dist: psycopg2 (==2.8.4) ; (platform_python_implementation == "CPython") and extra == 'test'
Requires-Dist: psycopg2cffi (==2.8.1) ; (platform_python_implementation == "PyPy") and extra == 'test'
Requires-Dist: gunicorn (==19.10.0) ; (python_version <= "3.3") and extra == 'test'
Requires-Dist: pytest (==4.6.9) ; (python_version <= "3.4") and extra == 'test'
Requires-Dist: mock (==3.0.5) ; (python_version <= "3.5") and extra == 'test'
Requires-Dist: pylint (==1.9.5) ; (python_version == "2.7.*") and extra == 'test'
Requires-Dist: docker (==4.2.0) ; (python_version == "2.7.*" or python_version >= "3.5") and extra == 'test'
Requires-Dist: tox (==3.14.5) ; (python_version == "2.7.*" or python_version >= "3.5") and extra == 'test'
Requires-Dist: docker (==3.7.3) ; (python_version == "3.4.*") and extra == 'test'
Requires-Dist: pylint (==2.3.1) ; (python_version == "3.4.*") and extra == 'test'
Requires-Dist: tox (==3.14.0) ; (python_version == "3.4.*") and extra == 'test'
Requires-Dist: gunicorn (==20.0.4) ; (python_version >= "3.4") and extra == 'test'
Requires-Dist: pylint (==2.4.4) ; (python_version >= "3.5") and extra == 'test'
Requires-Dist: pytest (==5.3.5) ; (python_version >= "3.5") and extra == 'test'
Requires-Dist: mock (==4.0.1) ; (python_version >= "3.6") and extra == 'test'
